odoo10_addon_l10n_es_account_bank_statement_import_n43-10.0.1.1.5-py2.7-nspkg.pth
odoo/addons/l10n_es_account_bank_statement_import_n43/README.rst
odoo/addons/l10n_es_account_bank_statement_import_n43/__init__.py
odoo/addons/l10n_es_account_bank_statement_import_n43/__manifest__.py
odoo/addons/l10n_es_account_bank_statement_import_n43/doc/norma_43_castellano.pdf
odoo/addons/l10n_es_account_bank_statement_import_n43/i18n/ca.po
odoo/addons/l10n_es_account_bank_statement_import_n43/i18n/es.po
odoo/addons/l10n_es_account_bank_statement_import_n43/i18n/es_ES.po
odoo/addons/l10n_es_account_bank_statement_import_n43/i18n/eu.po
odoo/addons/l10n_es_account_bank_statement_import_n43/i18n/gl.po
odoo/addons/l10n_es_account_bank_statement_import_n43/i18n/l10n_es_account_bank_statement_import_n43.pot
odoo/addons/l10n_es_account_bank_statement_import_n43/i18n/sl.po
odoo/addons/l10n_es_account_bank_statement_import_n43/models/__init__.py
odoo/addons/l10n_es_account_bank_statement_import_n43/models/account_journal.py
odoo/addons/l10n_es_account_bank_statement_import_n43/static/description/icon.png
odoo/addons/l10n_es_account_bank_statement_import_n43/static/description/icon_src.svg
odoo/addons/l10n_es_account_bank_statement_import_n43/tests/__init__.py
odoo/addons/l10n_es_account_bank_statement_import_n43/tests/test.n43
odoo/addons/l10n_es_account_bank_statement_import_n43/tests/test_l10n_es_account_bank_statement_import_n43.py
odoo/addons/l10n_es_account_bank_statement_import_n43/views/account_journal_views.xml
odoo/addons/l10n_es_account_bank_statement_import_n43/wizards/__init__.py
odoo/addons/l10n_es_account_bank_statement_import_n43/wizards/account_bank_statement_import_n43.py
odoo/addons/l10n_es_account_bank_statement_import_n43/wizards/account_bank_statement_import_view.xml
odoo10_addon_l10n_es_account_bank_statement_import_n43-10.0.1.1.5.dist-info/METADATA
odoo10_addon_l10n_es_account_bank_statement_import_n43-10.0.1.1.5.dist-info/RECORD
odoo10_addon_l10n_es_account_bank_statement_import_n43-10.0.1.1.5.dist-info/WHEEL
odoo10_addon_l10n_es_account_bank_statement_import_n43-10.0.1.1.5.dist-info/namespace_packages.txt
odoo10_addon_l10n_es_account_bank_statement_import_n43-10.0.1.1.5.dist-info/top_level.txt
