Metadata-Version: 2.1
Name: odoo10-addon-l10n-es-account-bank-statement-import-n43
Version: 10.0.1.1.5
Summary: Importación de extractos bancarios españoles (Norma 43)
Home-page: https://github.com/OCA/l10n-spain
Author: Spanish Localization Team,Tecnativa,Odoo Community Association (OCA)
Author-email: support@odoo-community.org
License: AGPL-3
Platform: UNKNOWN
Classifier: Programming Language :: Python
Classifier: Framework :: Odoo
Classifier: License :: OSI Approved :: GNU Affero General Public License v3
Requires-Python: ~=2.7
Requires-Dist: chardet
Requires-Dist: odoo (<10.1dev,>=10.0)
